{
  "tempo": 121,
  "local": "6gkzqf9vb",
  "produtos": [
    {
      "id": "3OwJpcgIe41K4ZvHqGi1cI0tXn7nbOqO1VfrEbwsCrPjAw17_hKjYSA4cFCDvEXaeHEFaA.kFMMt-agVbpKhRofBAvsvI099oar9170",
      "local": "6gkzqdwcrs0",
      "desc": "PARAFUSO CHIPBOARD 3 0X16 PHILIPS VILA",
      "ncm": "73181200",
      "cdanp": "0",
      "valor_desconto": "0.00",
      "valor_tabela": "0.10",
      "valor": "0.10",
      "datahora": "2025-03-13T15:38:34.640Z",
      "tempo": "há 15 dias",
      "distkm": "0.488",
      "gtin": "",
      "nrdoc": "00059178",
      "estabelecimento": {
        "codigo": "VbBXU9gOl59lrmy9typ-1kuiD9bOZ1n0VyGq95qcQ0k",
        "nm_fan": "ELECTRA",
        "nm_emp": "UTILIDADES FERROELETRICAS COM MAT ELETRICOS LTDA",
        "tp_logr": "RUA",
        "nm_logr": "CRUZ MACHADO",
        "nr_logr": "256",
        "complemento": "",
        "bairro": "CENTRO",
        "mun": "CURITIBA",
        "uf": "PR",
        "mesoreg": "",
        "microreg": ""
      }
    },
    {
      "id": "29iD-_XjpATWZeAVf5D1Qlb2Ja0EDJUngsXtCRCxce7hDhzKyor8atHTyLkojLNdcz-7zg.kFMMt-agVbpKhRofBAvsvI099oar9170",
      "local": "6gkzqdjvkm0",
      "desc": "PARAFUSO PARA MADEIRA PHILIPS 3 0X20MM",
      "ncm": "73181200",
      "cdanp": "0",
      "valor_desconto": "0.00",
      "valor_tabela": "0.10",
      "valor": "0.10",
      "datahora": "2025-03-13T17:16:08.099Z",
      "tempo": "há 15 dias",
      "distkm": "0.772",
      "gtin": "",
      "nrdoc": "00064759",
      "estabelecimento": {
        "codigo": "GQNggQZVSdZqvzYHb3jahyPk51n_S9CjmaYxyBxMWMc",
        "nm_fan": "QUARKS EQUIPAMENTOS",
        "nm_emp": "NEUSA DO CARMO SIMOES",
        "tp_logr": "ALD",
        "nm_logr": "CABRAL",
        "nr_logr": "44",
        "complemento": "LOJA 02",
        "bairro": "CENTRO",
        "mun": "CURITIBA",
        "uf": "PR",
        "mesoreg": "",
        "microreg": ""
      }
    },
    {
      "id": "sqnyR1BF0yaXdkZYH_jN3GIvWocsuMH9nFkKNoueO9i2cBWgAgwoownhdfh4AsTa71k_WA.kFMMt-agVbpKhRofBAvsvI099oar9170",
      "local": "6gkzqfpp020",
      "desc": "PARAFUSO PHILIPS CHIPBOARD 3 0 X 25MM",
      "ncm": "73181200",
      "cdanp": "0",
      "valor_desconto": "0.00",
      "valor_tabela": "0.10",
      "valor": "0.10",
      "datahora": "2025-03-19T13:36:08.106Z",
      "tempo": "há 9 dias",
      "distkm": "0.972",
      "gtin": "",
      "nrdoc": "00006956",
      "estabelecimento": {
        "codigo": "StoG1JRvnzsdiwgL5vLm11RRkLslNrWuz3TFwayRc6k",
        "nm_fan": "",
        "nm_emp": "MASTERLUZ MATERIAIS ELETRICOS LTDA",
        "tp_logr": "RUA",
        "nm_logr": "CONSELHEIRO LAURINDO",
        "nr_logr": "641",
        "complemento": "COND NSA GUADAL",
        "bairro": "CENTRO",
        "mun": "CURITIBA",
        "uf": "PR",
        "mesoreg": "",
        "microreg": ""
      }
    },
    {
      "id": "0C6r7EQrOoV5dX7EHHFal7O5mUswhBvH5ZL7WDdPIjb2cufQXL0_m1vROVc3UnYyo1Nf6w.kFMMt-agVbpKhRofBAvsvI099oar9170",
      "local": "6gkzqfpp020",
      "desc": "PARAFUSO PHILIPS CHIPBOARD 4 0X40MM BUCHA 6",
      "ncm": "73181200",
      "cdanp": "0",
      "valor_desconto": "0.00",
      "valor_tabela": "0.10",
      "valor": "0.10",
      "datahora": "2025-03-24T15:14:14.542Z",
      "tempo": "há 4 dias",
      "distkm": "0.972",
      "gtin": "",
      "nrdoc": "00007047",
      "estabelecimento": {
        "codigo": "StoG1JRvnzsdiwgL5vLm11RRkLslNrWuz3TFwayRc6k",
        "nm_fan": "",
        "nm_emp": "MASTERLUZ MATERIAIS ELETRICOS LTDA",
        "tp_logr": "RUA",
        "nm_logr": "CONSELHEIRO LAURINDO",
        "nr_logr": "641",
        "complemento": "COND NSA GUADAL",
        "bairro": "CENTRO",
        "mun": "CURITIBA",
        "uf": "PR",
        "mesoreg": "",
        "microreg": ""
      }
    },
    {
      "id": "jyKXFr2BfLRzccUOFrNPgh9IIJwTB_-Y4oeiBP5d7yjfKTiTdMFdFI5dOIqX8dH0KZxoew.kFMMt-agVbpKhRofBAvsvI099oar9170",
      "local": "6gkzqe19uj0",
      "desc": "PARAFUSO AA CHATA PHILIPS UN",
      "ncm": "73181200",
      "cdanp": "0",
      "valor_desconto": "0.00",
      "valor_tabela": "0.10",
      "valor": "0.10",
      "datahora": "2025-03-26T20:53:04.606Z",
      "tempo": "há 2 dias",
      "distkm": "1.430",
      "gtin": "",
      "nrdoc": "00307954",
      "estabelecimento": {
        "codigo": "CeiGWkw2KeBM01SQ48874LegZHrdvnMIh0ZqjKMCJu0",
        "nm_fan": "",
        "nm_emp": "BUCHHOLTZ & CIA LTDA",
        "tp_logr": "RUA",
        "nm_logr": "MARTIN AFONSO",
        "nr_logr": "491",
        "complemento": "",
        "bairro": "MERCES",
        "mun": "CURITIBA",
        "uf": "PR",
        "mesoreg": "",
        "microreg": ""
      }
    },
    {
      "id": "rkiyYmIT4DpkhkwTOKXnTxSAzjvdUmK70Uj9K6X2Ema6zmU6Dnbh21CojbB6jU_KnOn4qg.kFMMt-agVbpKhRofBAvsvI099oar9170",
      "local": "6gkzq8z8k70",
      "desc": "PARAFUSO FORRO CABECA PHILIPS FLANGEADA PONTA BROCA 4.2 X 16 P00817 ",
      "ncm": "73181400",
      "cdanp": "0",
      "valor_desconto": "0.00",
      "valor_tabela": "0.10",
      "valor": "0.10",
      "datahora": "2025-03-17T14:33:14.677Z",
      "tempo": "há 11 dias",
      "distkm": "1.510",
      "gtin": "",
      "nrdoc": "00057498",
      "estabelecimento": {
        "codigo": "Ro-jzYYN0mOov7Sdewl4Fwr8xOFFUj1ZDVRxpu8krZE",
        "nm_fan": "GANZERT FERRAGENS",
        "nm_emp": "GANZERT COMERCIO DE FERRAGENS LTDA",
        "tp_logr": "RUA",
        "nm_logr": "NUNES MACHADO",
        "nr_logr": "321",
        "complemento": "",
        "bairro": "CENTRO",
        "mun": "CURITIBA",
        "uf": "PR",
        "mesoreg": "",
        "microreg": ""
      }
    },
    {
      "id": "QDC25PGQ5YR57PNGXM9kwoftfKa4Aixd7mO_DBUDfjLY9VHU1fUmiqJP4qUC0i3r.kFMMt-agVbpKhRofBAvsvI099oar9170",
      "local": "6gkzqebxc50",
      "desc": "PARAFUSO CHIP 3 5X25 PRETO CISER CAB CHATA PHILIPS",
      "ncm": "73181200",
      "cdanp": "0",
      "valor_desconto": "0.00",
      "valor_tabela": "0.10",
      "valor": "0.10",
      "datahora": "2025-03-14T19:24:14.800Z",
      "tempo": "há 14 dias",
      "distkm": "1.880",
      "gtin": "",
      "nrdoc": "00087239",
      "estabelecimento": {
        "codigo": "GFkGfCnaalMNz0ViMjpuhucyBmTpFf1I4wfXsA",
        "nm_fan": "GERMINIANI E PEDROSO LTDA",
        "nm_emp": "VILAS BOAS & PEDROSO LTDA",
        "tp_logr": "RUA",
        "nm_logr": "MANOEL RIBAS",
        "nr_logr": "507",
        "complemento": "LJ 07",
        "bairro": "SAO FRANCISCO",
        "mun": "CURITIBA",
        "uf": "PR",
        "mesoreg": "",
        "microreg": ""
      }
    },
    {
      "id": "BMUwFPijudfAkUyHkYBfD6s_xDeI6mHrMQwcHXfTbn4hCkmjzY-KHGw3NEq2PZ9V.kFMMt-agVbpKhRofBAvsvI099oar9170",
      "local": "6gkzqebxc50",
      "desc": "PARAFUSO FLANGEADO 4 2X13 PONTA AGULHA VILA FORRO ",
      "ncm": "73181400",
      "cdanp": "0",
      "valor_desconto": "0.00",
      "valor_tabela": "0.10",
      "valor": "0.10",
      "datahora": "2025-03-14T11:14:32.217Z",
      "tempo": "há 15 dias",
      "distkm": "1.880",
      "gtin": "",
      "nrdoc": "00087198",
      "estabelecimento": {
        "codigo": "GFkGfCnaalMNz0ViMjpuhucyBmTpFf1I4wfXsA",
        "nm_fan": "GERMINIANI E PEDROSO LTDA",
        "nm_emp": "VILAS BOAS & PEDROSO LTDA",
        "tp_logr": "RUA",
        "nm_logr": "MANOEL RIBAS",
        "nr_logr": "507",
        "complemento": "LJ 07",
        "bairro": "SAO FRANCISCO",
        "mun": "CURITIBA",
        "uf": "PR",
        "mesoreg": "",
        "microreg": ""
      }
    },
    {
      "id": "j-yLyl5N50ndsja9O2_9zS9tUQJlTTi4aUNwxhaEC6cAr9CeKWqwCBY3qQRce_oU.kFMMt-agVbpKhRofBAvsvI099oar9170",
      "local": "6gkzqebxc50",
      "desc": "PARAFUSO CHIP 3 5X16",
      "ncm": "73181200",
      "cdanp": "0",
      "valor_desconto": "0.00",
      "valor_tabela": "0.10",
      "valor": "0.10",
      "datahora": "2025-03-18T19:39:13.350Z",
      "tempo": "há 10 dias",
      "distkm": "1.880",
      "gtin": "",
      "nrdoc": "00087323",
      "estabelecimento": {
        "codigo": "GFkGfCnaalMNz0ViMjpuhucyBmTpFf1I4wfXsA",
        "nm_fan": "GERMINIANI E PEDROSO LTDA",
        "nm_emp": "VILAS BOAS & PEDROSO LTDA",
        "tp_logr": "RUA",
        "nm_logr": "MANOEL RIBAS",
        "nr_logr": "507",
        "complemento": "LJ 07",
        "bairro": "SAO FRANCISCO",
        "mun": "CURITIBA",
        "uf": "PR",
        "mesoreg": "",
        "microreg": ""
      }
    },
    {
      "id": "0elAlmw51JthHg7bj44tGpJsc7dld2exfa9TmQiMiecZbz5bFbc9hdMqOXr5NA63zY0sYg.i5uRR8_PJJR6PnnHLKoJEW4JsOchNK-U",
      "local": "6gkzqc2zp20",
      "desc": "AA 4 2X16 PANELA PARAFUSO",
      "ncm": "73181200",
      "cdanp": "0",
      "valor_desconto": "0.00",
      "valor_tabela": "0.11",
      "valor": "0.11",
      "datahora": "2025-03-13T13:37:26.246Z",
      "tempo": "há 15 dias",
      "distkm": "0.934",
      "gtin": "",
      "nrdoc": "00163282",
      "estabelecimento": {
        "codigo": "_3v1y37jX6hMTIW_i0Syo38CER7jB7_B8TfGULc8_I4",
        "nm_fan": "",
        "nm_emp": "DISTRIBUIDORA FECHADURA LTDA",
        "tp_logr": "RUA",
        "nm_logr": "ANDRE DE BARROS",
        "nr_logr": "12",
        "complemento": "LOJA",
        "bairro": "CENTRO",
        "mun": "CURITIBA",
        "uf": "PR",
        "mesoreg": "",
        "microreg": ""
      }
    },
    {
      "id": "Ka938ImEr-HN3D6_ZQchj5mFweZV_GZDrQdjQaegK-Y35bJ4EJ8XZkSXIlfQp3dYbJQhUg.i5uRR8_PJJR6PnnHLKoJEW4JsOchNK-U",
      "local": "6gkzr1cxkb0",
      "desc": "PARAFUSO MADEIRA 2 8 X 12 FN",
      "ncm": "73181200",
      "cdanp": "0",
      "valor_desconto": "0.00",
      "valor_tabela": "0.11",
      "valor": "0.11",
      "datahora": "2025-03-19T14:21:48.619Z",
      "tempo": "há 9 dias",
      "distkm": "1.464",
      "gtin": "",
      "nrdoc": "00138349",
      "estabelecimento": {
        "codigo": "lkfXnVfxbNSc-OqIcNT2RHF0ueJ-dNbJtG5W3PVoAlM",
        "nm_fan": "REI DAS FECHADURAS",
        "nm_emp": "REI DAS FECHADURAS LTDA",
        "tp_logr": "AV",
        "nm_logr": "VISCONDE DE GUARAPUAVA",
        "nr_logr": "1915",
        "complemento": "",
        "bairro": "CENTRO",
        "mun": "CURITIBA",
        "uf": "PR",
        "mesoreg": "",
        "microreg": ""
      }
    },
    {
      "id": "WJRJTwUKxNlt-hl4A6r_Qfc0yoeiSoaK4zY0I06OZunIRzAoDXjljfAu41vpuPRk1MNOCw.UlMEsuJfHTccPBbyRtNjf2H09D3rqobq",
      "local": "6gkzqdj16h0",
      "desc": "PARAFUSO 4 X 12",
      "ncm": "73181100",
      "cdanp": "0",
      "valor_desconto": "0.00",
      "valor_tabela": "0.12",
      "valor": "0.12",
      "datahora": "2025-03-14T15:08:25.906Z",
      "tempo": "há 14 dias",
      "distkm": "0.943",
      "gtin": "",
      "nrdoc": "00082663",
      "estabelecimento": {
        "codigo": "Wm_AZj0lGEROy9yFzPZJazRmlYSQfTMl_dGutbFim-k",
        "nm_fan": "REI DO CHUVEIRO",
        "nm_emp": "REI DO CHUVEIRO MATS ELETRICOS E HIDRAULICOS LTDA",
        "tp_logr": "RUA",
        "nm_logr": "VISCONDE DE NACAR",
        "nr_logr": "1205",
        "complemento": "",
        "bairro": "CENTRO",
        "mun": "CURITIBA",
        "uf": "PR",
        "mesoreg": "",
        "microreg": ""
      }
    },
    {
      "id": "aFTdJC2tIoMbQxsXnmHfhFY9-dXC_b18DEsHRvp9Tq8Zzvtve9DuvtcdcAS4nNNIGiSfqw.UlMEsuJfHTccPBbyRtNjf2H09D3rqobq",
      "local": "6gkzqfpp020",
      "desc": "PARAFUSO BROCANTE FLANGEADO 4 2 X 13",
      "ncm": "73181400",
      "cdanp": "0",
      "valor_desconto": "0.00",
      "valor_tabela": "0.12",
      "valor": "0.12",
      "datahora": "2025-03-18T17:42:07.429Z",
      "tempo": "há 10 dias",
      "distkm": "0.972",
      "gtin": "",
      "nrdoc": "00006943",
      "estabelecimento": {
        "codigo": "StoG1JRvnzsdiwgL5vLm11RRkLslNrWuz3TFwayRc6k",
        "nm_fan": "",
        "nm_emp": "MASTERLUZ MATERIAIS ELETRICOS LTDA",
        "tp_logr": "RUA",
        "nm_logr": "CONSELHEIRO LAURINDO",
        "nr_logr": "641",
        "complemento": "COND NSA GUADAL",
        "bairro": "CENTRO",
        "mun": "CURITIBA",
        "uf": "PR",
        "mesoreg": "",
        "microreg": ""
      }
    }
  ],
  "total": 720,
  "precos": {
    "min": "0.10",
    "max": "139.10"
  }
}